LICENSE
MANIFEST.in
README.md
setup.py
django_meta_pages.egg-info/PKG-INFO
django_meta_pages.egg-info/SOURCES.txt
django_meta_pages.egg-info/dependency_links.txt
django_meta_pages.egg-info/requires.txt
django_meta_pages.egg-info/top_level.txt
meta_pages/__init__.py
meta_pages/admin.py
meta_pages/apps.py
meta_pages/context_processors.py
meta_pages/models.py
meta_pages/tests.py
meta_pages/migrations/0001_initial.py
meta_pages/migrations/__init__.py
meta_pages/templates/meta_pages/meta.html